LICENSE.txt
MANIFEST.in
README.rst
VERSION
setup.cfg
setup.py
tests/test_list_continuity.py
tests/test_mvp_api.py
treniformis/__init__.py
treniformis/_mvp_api.py
treniformis/errors.py
treniformis.egg-info/PKG-INFO
treniformis.egg-info/SOURCES.txt
treniformis.egg-info/dependency_links.txt
treniformis.egg-info/requires.txt
treniformis.egg-info/top_level.txt
treniformis.egg-info/zip-safe
treniformis/_assets/GFW/ACTIVE_MMSI/2012.txt
treniformis/_assets/GFW/ACTIVE_MMSI/2013.txt
treniformis/_assets/GFW/ACTIVE_MMSI/2014.txt
treniformis/_assets/GFW/ACTIVE_MMSI/2015.txt
treniformis/_assets/GFW/ACTIVE_MMSI/2016.txt
treniformis/_assets/GFW/ACTIVE_MMSI/2017.txt
treniformis/_assets/GFW/ACTIVE_MMSI/README.md
treniformis/_assets/GFW/FISHING_MMSI/KNOWN/2014.txt
treniformis/_assets/GFW/FISHING_MMSI/KNOWN/2015.txt
treniformis/_assets/GFW/FISHING_MMSI/KNOWN/README.md
treniformis/_assets/GFW/FISHING_MMSI/KNOWN_AND_LIKELY/2012.txt
treniformis/_assets/GFW/FISHING_MMSI/KNOWN_AND_LIKELY/2013.txt
treniformis/_assets/GFW/FISHING_MMSI/KNOWN_AND_LIKELY/2014.txt
treniformis/_assets/GFW/FISHING_MMSI/KNOWN_AND_LIKELY/2015.txt
treniformis/_assets/GFW/FISHING_MMSI/KNOWN_AND_LIKELY/2016.txt
treniformis/_assets/GFW/FISHING_MMSI/KNOWN_AND_LIKELY/2017.txt
treniformis/_assets/GFW/FISHING_MMSI/LIKELY/2012.txt
treniformis/_assets/GFW/FISHING_MMSI/LIKELY/2013.txt
treniformis/_assets/GFW/FISHING_MMSI/LIKELY/2014.txt
treniformis/_assets/GFW/FISHING_MMSI/LIKELY/2015.txt
treniformis/_assets/GFW/FISHING_MMSI/LIKELY/2016.txt
treniformis/_assets/GFW/FISHING_MMSI/LIKELY/2017.txt
treniformis/_assets/GFW/FISHING_MMSI/LIKELY/README.md
treniformis/_assets/GFW/SPOOFING_MMSI/2012.txt
treniformis/_assets/GFW/SPOOFING_MMSI/2013.txt
treniformis/_assets/GFW/SPOOFING_MMSI/2014.txt
treniformis/_assets/GFW/SPOOFING_MMSI/2015.txt
treniformis/_assets/GFW/SPOOFING_MMSI/2016.txt
treniformis/_assets/GFW/SPOOFING_MMSI/2017.txt
treniformis/_assets/GFW/SPOOFING_MMSI/README.md
treniformis/_assets/GFW/VESSEL_INFO/README.md
treniformis/_assets/GFW/VESSEL_INFO/REEFERS.csv