Metadata-Version: 1.1
Name: treniformis
Version: 0.4.0-6
Summary: Global Fishing Watch vessel lists
Home-page: https://github.com/GlobalFishingWatch/treniformis
Author: Global Fishing Watch
Author-email: info@globalfishingwatch.org
License: Apache 2.0
Keywords: GFW Global Fishing Watch vessel lists
Platform: UNKNOWN
Classifier: Development Status :: 1 - Planning
Classifier: Intended Audience :: Developers
Classifier: Intended Audience :: Information Technology
Classifier: Intended Audience :: Science/Research
Classifier: License :: OSI Approved :: Apache Software License
Classifier: Programming Language :: Python :: 2
Classifier: Programming Language :: Python :: 2.7
Classifier: Programming Language :: Python :: 3
Classifier: Programming Language :: Python :: 3.3
Classifier: Programming Language :: Python :: 3.4
Classifier: Programming Language :: Python :: 3.5
Classifier: Programming Language :: Python :: 3.6
Classifier: Topic :: Scientific/Engineering :: Information Analysis
